weeklyresearchdigest/__init__.py
weeklyresearchdigest/config.env
weeklyresearchdigest/config.py
weeklyresearchdigest/digest_logic.py
weeklyresearchdigest/scheduler.py
weeklyresearchdigest/weekly_digest.py
weeklyresearchdigest-0.1.4.dist-info/entry_points.txt
weeklyresearchdigest-0.1.4.dist-info/LICENSE
weeklyresearchdigest-0.1.4.dist-info/METADATA
weeklyresearchdigest-0.1.4.dist-info/WHEEL
weeklyresearchdigest-0.1.4.dist-info/RECORD
